ircbuilder/__init__.py
ircbuilder/building.py
ircbuilder/nodebuilder.py
ircbuilder/version.py
ircbuilder-0.0.12.dist-info/METADATA
ircbuilder-0.0.12.dist-info/WHEEL
ircbuilder-0.0.12.dist-info/top_level.txt
ircbuilder-0.0.12.dist-info/RECORD
