Metadata-Version: 2.1
Name: ircbuilder
Version: 0.0.12
Summary: Python API for Minetest server with irc_builder mod
Home-page: https://github.com/timcu/irc_builder
Author: D Tim Cummings
Author-email: dtimcummings@gmail.com
License: MIT
Keywords: minetest irc
Classifier: Development Status :: 4 - Beta
Classifier: Intended Audience :: Education
Classifier: Intended Audience :: Developers
Classifier: Topic :: Games/Entertainment
Classifier: License :: OSI Approved :: MIT License
Classifier: Programming Language :: Python :: 3
Classifier: Programming Language :: Python :: 3.6
Classifier: Programming Language :: Python :: 3.7
Classifier: Programming Language :: Python :: 3.8
Classifier: Programming Language :: Python :: 3.9
Classifier: Programming Language :: Python :: 3.10
Requires-Python: >=3.6
